pwi/__init__.py
pwi/axis.py
pwi/base.py
pwi/base_focuser.py
pwi/base_mount.py
pwi/calibration.py
pwi/client.py
pwi/common.py
pwi/mount.py
pwi/offsets.py
pwi/py.typed
pwi/response.py
pwi/serial.py
pwi/site.py
pwi/status.py
pwi/sun.py
pwi/units.py
pwi/utils.py
pwi/version.py
pwi-0.14.0.dist-info/METADATA
pwi-0.14.0.dist-info/WHEEL
pwi-0.14.0.dist-info/licenses/LICENSE
pwi-0.14.0.dist-info/RECORD
