Metadata-Version: 2.4
Name: pwi
Version: 0.14.0
Summary: Modern, type-safe, python library for controlling PlaneWave devices
Project-URL: Source, https://github.com/michealroberts/pwi
Project-URL: Issues, https://github.com/michealroberts/pwi/issues
Project-URL: PullRequests, https://github.com/michealroberts/pwi/pulls
Project-URL: Discussions, https://github.com/michealroberts/pwi/discussions
Author-email: michealroberts <michael@observerly.com>
License: MIT License
License-File: LICENSE
Keywords: astronomy,astrophotography,focuser,mount,observatory,planewave,pwi4,rotator,telescope
Classifier: Development Status :: 3 - Alpha
Classifier: Intended Audience :: Developers
Classifier: Intended Audience :: Science/Research
Classifier: License :: OSI Approved :: MIT License
Classifier: Natural Language :: English
Classifier: Operating System :: OS Independent
Classifier: Programming Language :: Python :: 3
Classifier: Programming Language :: Python :: 3.11
Classifier: Programming Language :: Python :: 3.12
Classifier: Programming Language :: Python :: 3.13
Requires-Python: >=3.11
Requires-Dist: celerity>=0.39.0
Requires-Dist: httpx>=0.28.1
Requires-Dist: pydantic>=2.12.4
Requires-Dist: satelles>=0.20.0
Requires-Dist: typing-extensions>=4.15.0
Requires-Dist: usbx>=0.8.1
